vaulter_py/__init__.py
vaulter_py/passvault.py
vaulter_py-0.0.2.dist-info/LICENSE.md
vaulter_py-0.0.2.dist-info/METADATA
vaulter_py-0.0.2.dist-info/WHEEL
vaulter_py-0.0.2.dist-info/entry_points.txt
vaulter_py-0.0.2.dist-info/top_level.txt
vaulter_py-0.0.2.dist-info/RECORD
