Metadata-Version: 2.1
Name: vaulter-py
Version: 0.0.2
Summary: VAULTERPY is a python program with which you can secure your precious passwords very easily.
Home-page: https://github.com/Shreejan-35/VAULTERPY
Author: Shreejan Dolai
Author-email: dolaishreejan@gmail.com
License: UNKNOWN
Project-URL: Bug Tracker, https://github.com/Shreejan-35/VAULTERPY/issues
Keywords: password manager,password,vaulter,py,manager,safe
Platform: UNKNOWN
Classifier: Programming Language :: Python :: 3
Classifier: License :: OSI Approved :: MIT License
Classifier: Operating System :: OS Independent
Requires-Python: >=3.6
License-File: LICENSE.md
Requires-Dist: cryptography
